{
  "111-111-111": {
    "date": "2024-08-05",
    "readings": [
      {
        "time": "01:30",
        "value": 97.085
      },
      {
        "time": "02:00",
        "value": 97.357
      },
      {
        "time": "02:30",
        "value": 97.537
      },
      {
        "time": "03:00",
        "value": 97.777
      },
      {
        "time": "03:30",
        "value": 98.286
      },
      {
        "time": "04:00",
        "value": 98.35
      },
      {
        "time": "04:30",
        "value": 98.954
      },
      {
        "time": "05:00",
        "value": 99.571
      },
      {
        "time": "05:30",
        "value": 100.482
      },
      {
        "time": "06:00",
        "value": 101.381
      },
      {
        "time": "06:30",
        "value": 101.702
      },
      {
        "time": "07:00",
        "value": 102.494
      },
      {
        "time": "07:30",
        "value": 103.397
      },
      {
        "time": "08:00",
        "value": 103.879
      },
      {
        "time": "08:30",
        "value": 104.403
      },
      {
        "time": "09:00",
        "value": 105.241
      },
      {
        "time": "09:30",
        "value": 105.725
      },
      {
        "time": "10:00",
        "value": 106.478
      },
      {
        "time": "10:30",
        "value": 107.016
      },
      {
        "time": "11:00",
        "value": 107.822
      },
      {
        "time": "11:30",
        "value": 108.648
      },
      {
        "time": "12:00",
        "value": 108.858
      },
      {
        "time": "12:30",
        "value": 109.779
      },
      {
        "time": "13:00",
        "value": 109.888
      },
      {
        "time": "13:30",
        "value": 110.255
      },
      {
        "time": "14:00",
        "value": 110.836
      },
      {
        "time": "14:30",
        "value": 111.195
      },
      {
        "time": "15:00",
        "value": 111.968
      },
      {
        "time": "15:30",
        "value": 112.073
      },
      {
        "time": "16:00",
        "value": 112.916
      },
      {
        "time": "16:30",
        "value": 113.062
      },
      {
        "time": "17:00",
        "value": 113.447
      },
      {
        "time": "17:30",
        "value": 113.969
      },
      {
        "time": "18:00",
        "value": 114.452
      },
      {
        "time": "18:30",
        "value": 114.536
      },
      {
        "time": "19:00",
        "value": 114.746
      },
      {
        "time": "19:30",
        "value": 115.734
      },
      {
        "time": "20:00",
        "value": 116.113
      },
      {
        "time": "20:30",
        "value": 116.592
      },
      {
        "time": "21:00",
        "value": 116.955
      },
      {
        "time": "21:30",
        "value": 117.724
      },
      {
        "time": "22:00",
        "value": 118.453
      },
      {
        "time": "22:30",
        "value": 118.648
      },
      {
        "time": "23:00",
        "value": 119.216
      },
      {
        "time": "23:30",
        "value": 119.37
      }
    ]
  },
  "333-333-333": {
    "date": "2024-08-05",
    "readings": [
      {
        "time": "01:30",
        "value": 87.333
      },
      {
        "time": "02:00",
        "value": 88.279
      },
      {
        "time": "02:30",
        "value": 88.343
      },
      {
        "time": "03:00",
        "value": 89.289
      },
      {
        "time": "03:30",
        "value": 90.046
      },
      {
        "time": "04:00",
        "value": 90.888
      },
      {
        "time": "04:30",
        "value": 91.652
      },
      {
        "time": "05:00",
        "value": 92.378
      },
      {
        "time": "05:30",
        "value": 92.684
      },
      {
        "time": "06:00",
        "value": 93.482
      },
      {
        "time": "06:30",
        "value": 93.516
      },
      {
        "time": "07:00",
        "value": 93.833
      },
      {
        "time": "07:30",
        "value": 94.833
      },
      {
        "time": "08:00",
        "value": 95.135
      },
      {
        "time": "08:30",
        "value": 95.344
      },
      {
        "time": "09:00",
        "value": 95.464
      },
      {
        "time": "09:30",
        "value": 96.059
      },
      {
        "time": "10:00",
        "value": 96.431
      },
      {
        "time": "10:30",
        "value": 97.239
      },
      {
        "time": "11:00",
        "value": 97.41
      },
      {
        "time": "11:30",
        "value": 97.637
      },
      {
        "time": "12:00",
        "value": 98.578
      },
      {
        "time": "12:30",
        "value": 98.853
      },
      {
        "time": "13:00",
        "value": 98.991
      },
      {
        "time": "13:30",
        "value": 99.468
      },
      {
        "time": "14:00",
        "value": 99.634
      },
      {
        "time": "14:30",
        "value": 100.523
      },
      {
        "time": "15:00",
        "value": 101.399
      },
      {
        "time": "15:30",
        "value": 101.588
      },
      {
        "time": "16:00",
        "value": 102.146
      },
      {
        "time": "16:30",
        "value": 102.546
      },
      {
        "time": "17:00",
        "value": 103.51
      },
      {
        "time": "17:30",
        "value": 104.112
      },
      {
        "time": "18:00",
        "value": 104.635
      },
      {
        "time": "18:30",
        "value": 104.915
      },
      {
        "time": "19:00",
        "value": 105.914
      },
      {
        "time": "19:30",
        "value": 106.256
      },
      {
        "time": "20:00",
        "value": 107.224
      },
      {
        "time": "20:30",
        "value": 107.644
      },
      {
        "time": "21:00",
        "value": 108.377
      },
      {
        "time": "21:30",
        "value": 109.212
      },
      {
        "time": "22:00",
        "value": 109.838
      },
      {
        "time": "22:30",
        "value": 109.861
      },
      {
        "time": "23:00",
        "value": 110.178
      },
      {
        "time": "23:30",
        "value": 110.607
      }
    ]
  },
  "666-666-666": {
    "date": "2024-08-05",
    "readings": [
      {
        "time": "01:30",
        "value": 96.334
      },
      {
        "time": "02:00",
        "value": 96.687
      },
      {
        "time": "02:30",
        "value": 97.055
      },
      {
        "time": "03:00",
        "value": 97.122
      },
      {
        "time": "03:30",
        "value": 97.164
      },
      {
        "time": "04:00",
        "value": 97.788
      },
      {
        "time": "04:30",
        "value": 98.764
      },
      {
        "time": "05:00",
        "value": 99.486
      },
      {
        "time": "05:30",
        "value": 99.846
      },
      {
        "time": "06:00",
        "value": 100.505
      },
      {
        "time": "06:30",
        "value": 101.121
      },
      {
        "time": "07:00",
        "value": 101.13
      },
      {
        "time": "07:30",
        "value": 101.298
      },
      {
        "time": "08:00",
        "value": 102.233
      },
      {
        "time": "08:30",
        "value": 102.245
      },
      {
        "time": "09:00",
        "value": 102.649
      },
      {
        "time": "09:30",
        "value": 103.099
      },
      {
        "time": "10:00",
        "value": 103.932
      },
      {
        "time": "10:30",
        "value": 104.278
      },
      {
        "time": "11:00",
        "value": 104.369
      },
      {
        "time": "11:30",
        "value": 104.621
      },
      {
        "time": "12:00",
        "value": 104.699
      },
      {
        "time": "12:30",
        "value": 105.639
      },
      {
        "time": "13:00",
        "value": 105.655
      },
      {
        "time": "13:30",
        "value": 106.161
      },
      {
        "time": "14:00",
        "value": 106.225
      },
      {
        "time": "14:30",
        "value": 106.937
      },
      {
        "time": "15:00",
        "value": 107.524
      },
      {
        "time": "15:30",
        "value": 107.645
      },
      {
        "time": "16:00",
        "value": 108.128
      },
      {
        "time": "16:30",
        "value": 108.626
      },
      {
        "time": "17:00",
        "value": 108.944
      },
      {
        "time": "17:30",
        "value": 109.204
      },
      {
        "time": "18:00",
        "value": 109.671
      },
      {
        "time": "18:30",
        "value": 109.97
      },
      {
        "time": "19:00",
        "value": 110.512
      },
      {
        "time": "19:30",
        "value": 111.267
      },
      {
        "time": "20:00",
        "value": 111.903
      },
      {
        "time": "20:30",
        "value": 112.063
      },
      {
        "time": "21:00",
        "value": 112.668
      },
      {
        "time": "21:30",
        "value": 113.584
      },
      {
        "time": "22:00",
        "value": 114.051
      },
      {
        "time": "22:30",
        "value": 114.46
      },
      {
        "time": "23:00",
        "value": 114.553
      },
      {
        "time": "23:30",
        "value": 115.254
      }
    ]
  }
}