{
  "111-111-111": {
    "date": "2025-04-12",
    "readings": [
      {
        "time": "11:30",
        "value": 0.234
      },
      {
        "time": "12:00",
        "value": 1.037
      },
      {
        "time": "12:30",
        "value": 1.061
      },
      {
        "time": "13:00",
        "value": 1.374
      },
      {
        "time": "13:30",
        "value": 1.654
      },
      {
        "time": "14:00",
        "value": 2.576
      },
      {
        "time": "14:30",
        "value": 2.867
      },
      {
        "time": "15:00",
        "value": 3.111
      },
      {
        "time": "15:30",
        "value": 3.8
      },
      {
        "time": "16:00",
        "value": 4.138
      },
      {
        "time": "16:30",
        "value": 4.55
      },
      {
        "time": "17:00",
        "value": 4.641
      },
      {
        "time": "17:30",
        "value": 5.078
      },
      {
        "time": "18:00",
        "value": 5.223
      },
      {
        "time": "18:30",
        "value": 5.53
      },
      {
        "time": "19:00",
        "value": 6.018
      },
      {
        "time": "19:30",
        "value": 6.886
      },
      {
        "time": "20:00",
        "value": 7.508
      },
      {
        "time": "20:30",
        "value": 7.942
      },
      {
        "time": "21:00",
        "value": 8.94
      },
      {
        "time": "21:30",
        "value": 9.584
      },
      {
        "time": "22:00",
        "value": 10.174
      },
      {
        "time": "22:30",
        "value": 11.043
      },
      {
        "time": "23:00",
        "value": 11.161
      },
      {
        "time": "23:30",
        "value": 11.166
      }
    ]
  }
}